miniirc_discord.py
miniirc_discord-0.6.2.dist-info/LICENSE.md
miniirc_discord-0.6.2.dist-info/METADATA
miniirc_discord-0.6.2.dist-info/WHEEL
miniirc_discord-0.6.2.dist-info/top_level.txt
miniirc_discord-0.6.2.dist-info/RECORD
